aiofiles/__init__.py
aiofiles/_compat.py
aiofiles/base.py
aiofiles/os.py
aiofiles/threadpool/__init__.py
aiofiles/threadpool/binary.py
aiofiles/threadpool/text.py
aiofiles/threadpool/utils.py
aiofiles-0.5.0.dist-info/LICENSE
aiofiles-0.5.0.dist-info/METADATA
aiofiles-0.5.0.dist-info/WHEEL
aiofiles-0.5.0.dist-info/top_level.txt
aiofiles-0.5.0.dist-info/RECORD
