Metadata-Version: 1.1
Name: aiofiles
Version: 0.5.0
Summary: File support for asyncio.
Home-page: https://github.com/Tinche/aiofiles
Author: Tin Tvrtkovic
Author-email: tinchester@gmail.com
License: Apache 2.0
Platform: UNKNOWN
Classifier: Development Status :: 4 - Beta
Classifier: Intended Audience :: Developers
Classifier: License :: OSI Approved :: Apache Software License
Classifier: Programming Language :: Python :: 3.5
Classifier: Programming Language :: Python :: 3.6
Classifier: Programming Language :: Python :: 3.7
Classifier: Programming Language :: Python :: 3.8
Classifier: Topic :: System :: Filesystems
